emonic/__init__.py
emonic/__version__.py
emonic/Restful/__init__.py
emonic/Restful/auth.py
emonic/Restful/exceptions.py
emonic/Restful/fields.py
emonic/Restful/inputs.py
emonic/Restful/requestParser.py
emonic/Restful/response.py
emonic/Restful/restful.py
emonic/Restful/middlewares/__init__.py
emonic/Restful/middlewares/middleware.py
emonic/admin/__init__.py
emonic/admin/admin.py
emonic/assets/__init__.py
emonic/assets/assets.py
emonic/cache/__init__.py
emonic/cache/cache.py
emonic/colours/__init__.py
emonic/colours/pkl.py
emonic/components/__init__.py
emonic/components/blueprint.py
emonic/components/cookies.py
emonic/components/sessions.py
emonic/contrib/BaseModal.py
emonic/contrib/__init__.py
emonic/core/__init__.py
emonic/core/branch.py
emonic/cors/__init__.py
emonic/cors/cors.py
emonic/crypter/__init__.py
emonic/crypter/crypt.py
emonic/csv/__init__.py
emonic/csv/csv.py
emonic/globals/__init__.py
emonic/globals/envion.py
emonic/http/__init__.py
emonic/http/requests/HttpAuth.py
emonic/http/requests/__init__.py
emonic/http/requests/requests.py
emonic/http/requests/sessions.py
emonic/jsonRPC/__init__.py
emonic/jsonRPC/rpc.py
emonic/limiter/__init__.py
emonic/limiter/limiter.py
emonic/mail/__init__.py
emonic/mail/mail.py
emonic/multiprocesser/__init__.py
emonic/multiprocesser/multiprocess.py
emonic/notify/__init__.py
emonic/notify/notify.py
emonic/principal/__init__.py
emonic/principal/principal.py
emonic/pydantic/__init__.py
emonic/pydantic/py.py
emonic/scheduler/__init__.py
emonic/scheduler/aps.py
emonic/security/__init__.py
emonic/security/JwT/__init__.py
emonic/security/JwT/jwt.py
emonic/security/csrf/__init__.py
emonic/security/csrf/csrf.py
emonic/sessions/__init__.py
emonic/sessions/localSession.py
emonic/socketio/__init__.py
emonic/socketio/socket.py
emonic/socketio/namespace/__init__.py
emonic/socketio/namespace/brick.py
emonic/tailsman/__init__.py
emonic/tailsman/csp.py
emonic/totp/__init__.py
emonic/totp/totp.py
emonic/uploadset/__init__.py
Emonic-1.0.5.dist-info/LICENSE
Emonic-1.0.5.dist-info/METADATA
Emonic-1.0.5.dist-info/WHEEL
Emonic-1.0.5.dist-info/entry_points.txt
Emonic-1.0.5.dist-info/top_level.txt
Emonic-1.0.5.dist-info/RECORD
