Metadata-Version: 2.1
Name: Emonic
Version: 1.0.5
Summary: Discover a user-friendly Python web framework designed to empower developers in building both standard and high-level applications. Crafted with simplicity in mind, this framework provides an intuitive environment for creating web applications that adhere to industry standards. Whether you're embarking on a straightforward project or aiming for a sophisticated application, our framework streamlines the development process, offering flexibility and tools to match your goals.
Home-page: https://github.com/embrake/emonic/
Author: Pawan kumar
Author-email: embrakeproject@gmail.com
License: MIT
Keywords: web framework Python web development user-friendly high-level
Classifier: Development Status :: 5 - Production/Stable
Classifier: License :: OSI Approved :: MIT License
Classifier: Programming Language :: Python :: 3
Classifier: Programming Language :: Python :: 3.6
Classifier: Programming Language :: Python :: 3.7
Classifier: Programming Language :: Python :: 3.8
Classifier: Programming Language :: Python :: 3.9
License-File: LICENSE
Requires-Dist: bcrypt
Requires-Dist: colorama
Requires-Dist: cryptography
Requires-Dist: itsdangerous
Requires-Dist: jinja2
Requires-Dist: qrcode
Requires-Dist: uuid
Requires-Dist: werkzeug
